dfreduce/__init__.py
dfreduce/core.py
dfreduce-1.7.dist-info/LICENSE
dfreduce-1.7.dist-info/METADATA
dfreduce-1.7.dist-info/WHEEL
dfreduce-1.7.dist-info/top_level.txt
dfreduce-1.7.dist-info/RECORD
