Metadata-Version: 2.1
Name: dfreduce
Version: 1.7
Summary: Automatic size reduction for pandas dataframe
Home-page: https://github.com/arun-nemani/dfreduce
Author: Arun Nemani
Author-email: neman014@gmail.com
License: UNKNOWN
Platform: UNKNOWN
Classifier: Programming Language :: Python :: 3
Classifier: License :: OSI Approved :: MIT License
Classifier: Operating System :: OS Independent
Requires-Dist: pandas (>=0.19)
Requires-Dist: numpy
Requires-Dist: nose
Requires-Dist: tqdm
